MANIFEST.in
README.md
setup.cfg
setup.py
urbackup_api/__init__.py
urbackup_server_web_api_wrapper.egg-info/PKG-INFO
urbackup_server_web_api_wrapper.egg-info/SOURCES.txt
urbackup_server_web_api_wrapper.egg-info/dependency_links.txt
urbackup_server_web_api_wrapper.egg-info/requires.txt
urbackup_server_web_api_wrapper.egg-info/top_level.txt