Metadata-Version: 2.1
Name: urbackup-server-web-api-wrapper
Version: 0.11
Summary: Python wrapper to access and control an UrBackup server
Home-page: https://github.com/uroni/urbackup-server-python-web-api-wrapper
Author: Martin Raiber
Author-email: martin@urbackup.org
License: Apache License 2.0
Keywords: urbackup web api client
Platform: UNKNOWN
Classifier: Development Status :: 3 - Alpha
Classifier: Intended Audience :: Developers
Classifier: License :: OSI Approved :: Apache Software License
Classifier: Programming Language :: Python :: 3.4
Classifier: Programming Language :: Python :: 3.5
Provides-Extra: dev
Provides-Extra: test
